alith-0.12.3.dist-info/METADATA
alith-0.12.3.dist-info/WHEEL
alith-0.12.3.dist-info/licenses/LICENSE
alith/__init__.py
alith/_alith.cp313-win_amd64.pyd
alith/agent.py
alith/chunking.py
alith/data/__init__.py
alith/data/crypto.py
alith/data/dataset_info.json
alith/data/download.py
alith/data/evaluator/__init__.py
alith/data/evaluator/text.py
alith/data/identity.json
alith/data/storage/__init__.py
alith/data/storage/interfaces.py
alith/data/storage/ipfs.py
alith/embeddings.py
alith/extractor.py
alith/inference/__init__.py
alith/inference/config.py
alith/inference/engines/__init__.py
alith/inference/engines/llamacpp.py
alith/inference/engines/ort.py
alith/inference/engines/python.py
alith/inference/engines/sglang.py
alith/inference/engines/vllm.py
alith/inference/proxy_server.py
alith/inference/query.py
alith/inference/server.py
alith/inference/settlement.py
alith/lazai/__init__.py
alith/lazai/chain.py
alith/lazai/client.py
alith/lazai/contracts.py
alith/lazai/node/__init__.py
alith/lazai/node/evaluator.py
alith/lazai/node/middleware.py
alith/lazai/node/types.py
alith/lazai/node/validator.py
alith/lazai/proof.py
alith/lazai/request.py
alith/lazai/settlement.py
alith/memory.py
alith/query/__init__.py
alith/query/config.py
alith/query/server.py
alith/query/settlement.py
alith/query/types.py
alith/store.py
alith/tee/__init__.py
alith/tee/marlin.py
alith/tee/phala.py
alith/tool.py
alith/training/__init__.py
alith/training/common.py
alith/training/errors.py
alith/training/server.py
alith/training/service.py
alith/training/trainer.py
alith/training/types.py
alith/types.py
alith-0.12.3.dist-info/RECORD
