Metadata-Version: 2.4
Name: alith
Version: 0.12.3
Classifier: Programming Language :: Rust
Classifier: Programming Language :: Python :: Implementation :: CPython
Classifier: Programming Language :: Python :: Implementation :: PyPy
Requires-Dist: pydantic
Requires-Dist: pydantic-config
Requires-Dist: requests
Requires-Dist: web3>=7.6.0,<8.0.0
Requires-Dist: rsa
Requires-Dist: python-gnupg
Requires-Dist: aiohttp
Requires-Dist: flask
Requires-Dist: uvicorn
Requires-Dist: fastapi
Requires-Dist: numpy
Requires-Dist: dstack-sdk>=0.2.1,<0.3.0
Requires-Dist: ruff ; extra == 'dev'
Requires-Dist: black ; extra == 'dev'
Requires-Dist: isort ; extra == 'dev'
Provides-Extra: dev
License-File: LICENSE
Summary: Alith Python SDK
License: Apache-2.0
Requires-Python: >=3.7
